LICENSE.md
README.md
orbit_component_zerodocs/__init__.py
orbit_component_zerodocs/doc_python.py
orbit_component_zerodocs/plugin.py
orbit_component_zerodocs/schema/APIs.py
orbit_component_zerodocs/schema/Cache.py
orbit_component_zerodocs/schema/Project.py
orbit_component_zerodocs/schema/Versions.py
orbit_component_zerodocs/version.py
orbit_component_zerodocs-1.0.90.dist-info/LICENSE.md
orbit_component_zerodocs-1.0.90.dist-info/METADATA
orbit_component_zerodocs-1.0.90.dist-info/WHEEL
orbit_component_zerodocs-1.0.90.dist-info/RECORD
